setup.py
mwscan/__init__.py
mwscan/ruleset.py
mwscan/scan.py
mwscan/settings.py
mwscan.egg-info/PKG-INFO
mwscan.egg-info/SOURCES.txt
mwscan.egg-info/dependency_links.txt
mwscan.egg-info/entry_points.txt
mwscan.egg-info/requires.txt
mwscan.egg-info/top_level.txt