Metadata-Version: 1.1
Name: mwscan
Version: 20181220.165251
Summary: Find malware in web documents.
Home-page: https://github.com/gwillem/magento-malware-scanner
Author: Willem de Groot
Author-email: gwillem@gmail.com
License: GPLv3
Download-URL: https://github.com/gwillem/magento-malware-scanner/tarball/20181220.165251
Keywords: yara,malware,magento
Platform: UNKNOWN
